.clang-format
.flake8
.gitignore
.gitmodules
CHANGELOG.md
CODEOWNERS
CODE_OF_CONDUCT
Dockerfile
Dockerfile-cuda
Dockerfile-embedded
LICENSE
MANIFEST.in
Makefile
README.md
__init__.py
description.txt
packages.txt
setup.py
./src/opendr/__init__.py
./src/opendr/_setup.py
./src/opendr/_version.py
./src/opendr/control/__init__.py
./src/opendr/engine/__init__.py
./src/opendr/engine/constants.py
./src/opendr/engine/data.py
./src/opendr/engine/datasets.py
./src/opendr/engine/example_learner.py
./src/opendr/engine/learners.py
./src/opendr/engine/target.py
./src/opendr/perception/__init__.py
./src/opendr/perception/compressive_learning/__init__.py
./src/opendr/perception/compressive_learning/dependencies.ini
./src/opendr/perception/compressive_learning/multilinear_compressive_learning/README.md
./src/opendr/perception/compressive_learning/multilinear_compressive_learning/__init__.py
./src/opendr/perception/compressive_learning/multilinear_compressive_learning/multilinear_compressive_learner.py
./src/opendr/perception/compressive_learning/multilinear_compressive_learning/algorithm/__init__.py
./src/opendr/perception/compressive_learning/multilinear_compressive_learning/algorithm/data.py
./src/opendr/perception/compressive_learning/multilinear_compressive_learning/algorithm/learner.py
./src/opendr/perception/compressive_learning/multilinear_compressive_learning/algorithm/trainers.py
./src/opendr/perception/compressive_learning/multilinear_compressive_learning/algorithm/backbones/__init__.py
./src/opendr/perception/compressive_learning/multilinear_compressive_learning/algorithm/backbones/cifar_allcnn.py
./src/opendr/perception/compressive_learning/multilinear_compressive_learning/algorithm/backbones/cifar_densenet.py
./src/opendr/perception/compressive_learning/multilinear_compressive_learning/algorithm/backbones/cifar_resnet.py
./src/opendr/perception/compressive_learning/multilinear_compressive_learning/algorithm/backbones/cifar_vgg.py
./src/opendr_toolkit_compressive_learning.egg-info/PKG-INFO
./src/opendr_toolkit_compressive_learning.egg-info/SOURCES.txt
./src/opendr_toolkit_compressive_learning.egg-info/dependency_links.txt
./src/opendr_toolkit_compressive_learning.egg-info/requires.txt
./src/opendr_toolkit_compressive_learning.egg-info/top_level.txt
